ait/__init__.py
ait/_common.py
ait/_linux.py
ait/_windows.py
ait/ait.py
ait/logger.py
ait/version.py
autoit-0.2.6.dist-info/METADATA
autoit-0.2.6.dist-info/WHEEL
autoit-0.2.6.dist-info/top_level.txt
autoit-0.2.6.dist-info/RECORD
