Metadata-Version: 2.1
Name: autoit
Version: 0.2.6
Summary: Automate it with Python
Home-page: https://github.com/Lonami/autoit
Author: Lonami Exo
Author-email: totufals@hotmail.com
License: MIT
Download-URL: https://github.com/Lonami/autoit/releases
Keywords: gui mouse keyboard automation automate
Platform: UNKNOWN
Classifier: Development Status :: 3 - Alpha
Classifier: Intended Audience :: Developers
Classifier: Topic :: Communications :: Chat
Classifier: License :: OSI Approved :: MIT License
Classifier: Programming Language :: Python :: 3
Classifier: Programming Language :: Python :: 3.5
Classifier: Programming Language :: Python :: 3.6
Requires-Python: >=3.5
